libsshfp/__init__.py
libsshfp/sshfp.py
libsshfp-0.0.3.dist-info/LICENSE
libsshfp-0.0.3.dist-info/METADATA
libsshfp-0.0.3.dist-info/WHEEL
libsshfp-0.0.3.dist-info/top_level.txt
libsshfp-0.0.3.dist-info/RECORD
