Metadata-Version: 2.1
Name: libsshfp
Version: 0.0.3
Summary: A tiny library to handle and validate SSHFP DNS records.
Author-email: Sebastian Neef <code@gehaxelt.in>
License: Copyright (c) 2018 The Python Packaging Authority        
Project-URL: Homepage, https://github.com/gehaxelt/python-libsshfp
Project-URL: Bug Tracker, https://github.com/gehaxelt/python-libsshfp/issues
Classifier: Programming Language :: Python :: 3
Classifier: License :: OSI Approved :: MIT License
Classifier: Operating System :: OS Independent
Requires-Python: >=3.7
License-File: LICENSE
